{"cameraMode":{"drawMode":0,"name":"Shaded","section":"Shading Mode"},"sceneLighting":true,"audioPlay":false,"sceneViewState":{"m_AlwaysRefresh":false,"showFog":true,"showSkybox":true,"showFlares":true,"showImageEffects":true,"showParticleSystems":true,"showVisualEffectGraphs":true,"m_FxEnabled":true},"in2DMode":false,"pivot":{"x":4.926941394805908,"y":5.781089782714844,"z":-11.168102264404297},"rotation":{"x":-0.060676395893096927,"y":0.936333954334259,"z":-0.2028149515390396,"w":-0.2801281213760376},"size":12.027311325073243,"orthographic":false}